src/__init__.py
src/commit_msg_checker.py
commit_msg_checker-0.1.0.dist-info/METADATA
commit_msg_checker-0.1.0.dist-info/WHEEL
commit_msg_checker-0.1.0.dist-info/entry_points.txt
commit_msg_checker-0.1.0.dist-info/RECORD
