Metadata-Version: 2.1
Name: commit-msg-checker
Version: 0.1.0
Summary: for adoc commit-msg-checker
License: Proprietary
Author: yongineer1990
Author-email: yongineer1990@gmail.com
Requires-Python: >=3.9,<4.0
Classifier: License :: Other/Proprietary License
Classifier: Programming Language :: Python :: 3
Classifier: Programming Language :: Python :: 3.9
Classifier: Programming Language :: Python :: 3.10
Classifier: Programming Language :: Python :: 3.11
Requires-Dist: pre-commit
